handbrake/__init__.py
handbrake/canceller.py
handbrake/errors.py
handbrake/mock.py
handbrake/models/__init__.py
handbrake/models/common.py
handbrake/models/preset.py
handbrake/models/progress.py
handbrake/models/title.py
handbrake/models/version.py
handbrake/opts.py
handbrake/progresshandler.py
handbrake/py.typed
handbrake/runner.py
handbrake/utils.py
pyhandbrake-2.0.1.dist-info/METADATA
pyhandbrake-2.0.1.dist-info/WHEEL
pyhandbrake-2.0.1.dist-info/licenses/LICENSE
pyhandbrake-2.0.1.dist-info/RECORD
