Metadata-Version: 2.4
Name: pyhandbrake
Version: 2.0.1
Summary: Python library to interface with HandBrakeCLI
License: MIT
License-File: LICENSE
Keywords: handbrake,dvd,bluray,multimedia,convert,video,audio
Author: Dominic Price
Author-email: dominicprice@outlook.com
Requires-Python: >=3.10,<4.0
Classifier: Development Status :: 4 - Beta
Classifier: Environment :: Console
Classifier: License :: OSI Approved :: MIT License
Classifier: Natural Language :: English
Classifier: Operating System :: OS Independent
Classifier: Programming Language :: Python :: 3
Classifier: Programming Language :: Python :: 3.10
Classifier: Programming Language :: Python :: 3.11
Classifier: Programming Language :: Python :: 3.12
Classifier: Programming Language :: Python :: 3.13
Classifier: Programming Language :: Python :: 3.14
Requires-Dist: pydantic (>=2.9.2,<3.0.0)
Project-URL: Bug Tracker, https://github.com/dominicprice/pyhandbrake/issues
Project-URL: Documentation, https://github.com/dominicprice/pyhandbrake
Project-URL: Homepage, https://github.com/dominicprice/pyhandbrake
